gencat
gslab_fill
gslab_make
gslab_scons
