Metadata-Version: 1.1
Name: GSLab-Tools
Version: 1.1.1
Summary: Python tools for GSLab
Home-page: https://github.com/gslab-econ/gslab_python
Author: Matthew Gentzkow, Jesse Shapiro
Author-email: gentzkow@stanford.edu, jesse_shapiro_1@brown.edu
License: MIT
Download-URL: https://github.com/gslab-econ/gslab_python/archive/v1.1.1.tar.gz
Platform: UNKNOWN
